arachnys_api_client/__init__.py
arachnys_api_client/__main__.py
arachnys_api_client/client.py
arachnys_api_client/py.typed
arachnys_api_client-0.1.0.dist-info/entry_points.txt
arachnys_api_client-0.1.0.dist-info/LICENSE
arachnys_api_client-0.1.0.dist-info/WHEEL
arachnys_api_client-0.1.0.dist-info/METADATA
arachnys_api_client-0.1.0.dist-info/RECORD
