Metadata-Version: 2.1
Name: arachnys-api-client
Version: 0.1.0
Summary: API client for Arachnys APIs, including Unified Search, Entity API and otherss
Home-page: https://github.com/arachnys/arachnys-api-client
License: MIT
Author: Arachnys
Author-email: info@arachnys.com
Requires-Python: >=3.7,<4.0
Classifier: Development Status :: 3 - Alpha
Classifier: Intended Audience :: Developers
Classifier: License :: OSI Approved :: MIT License
Classifier: Operating System :: OS Independent
Classifier: Programming Language :: Python :: 3
Classifier: Programming Language :: Python :: 3.7
Classifier: Programming Language :: Python :: 3.8
Classifier: Topic :: Software Development :: Libraries :: Python Modules
Requires-Dist: importlib_metadata (>=1.6.0,<2.0.0); python_version < "3.8"
Requires-Dist: ipdb (>=0.13.4,<0.14.0)
Requires-Dist: mock (>=4.0.2,<5.0.0)
Requires-Dist: requests (>=2.25.0,<3.0.0)
Requires-Dist: responses (>=0.12.1,<0.13.0)
Requires-Dist: rich (>=8.0.0,<9.0.0)
Requires-Dist: typer[all] (>=0.3.2,<0.4.0)
Project-URL: Repository, https://github.com/arachnys/arachnys-api-client
